{
  "_format": "hh-sol-cache-2",
  "files": {
    "/home/jistriane/Documentos/StreamPay AI/StreamPay-AI/smart-contracts/contracts/ERC20Mock.sol": {
      "lastModificationDate": 1765495671297,
      "contentHash": "7f31da15875718ec82675a12712d5710",
      "sourceName": "contracts/ERC20Mock.sol",
      "solcConfig": {
        "version": "0.8.20",
        "settings": {
          "optimizer": {
            "enabled": true,
            "runs": 200
          },
          "viaIR": true,
          "evmVersion": "paris",
          "outputSelection": {
            "*": {
              "*": [
                "abi",
                "evm.bytecode",
                "evm.deployedBytecode",
                "evm.methodIdentifiers",
                "metadata"
              ],
              "": [
                "ast"
              ]
            }
          }
        }
      },
      "imports": [
        "@openzeppelin/contracts/token/ERC20/ERC20.sol"
      ],
      "versionPragmas": [
        "^0.8.20"
      ],
      "artifacts": [
        "ERC20Mock"
      ]
    },
    "/home/jistriane/Documentos/StreamPay AI/StreamPay-AI/smart-contracts/node_modules/@openzeppelin/contracts/token/ERC20/ERC20.sol": {
      "lastModificationDate": 1765496181267,
      "contentHash": "3ae5166c6827a9cf1a7a462d1632b464",
      "sourceName": "@openzeppelin/contracts/token/ERC20/ERC20.sol",
      "solcConfig": {
        "version": "0.8.20",
        "settings": {
          "optimizer": {
            "enabled": true,
            "runs": 200
          },
          "viaIR": true,
          "evmVersion": "paris",
          "outputSelection": {
            "*": {
              "*": [
                "abi",
                "evm.bytecode",
                "evm.deployedBytecode",
                "evm.methodIdentifiers",
                "metadata"
              ],
              "": [
                "ast"
              ]
            }
          }
        }
      },
      "imports": [
        "./IERC20.sol",
        "./extensions/IERC20Metadata.sol",
        "../../utils/Context.sol"
      ],
      "versionPragmas": [
        "^0.8.0"
      ],
      "artifacts": [
        "ERC20"
      ]
    },
    "/home/jistriane/Documentos/StreamPay AI/StreamPay-AI/smart-contracts/node_modules/@openzeppelin/contracts/token/ERC20/IERC20.sol": {
      "lastModificationDate": 1765496182683,
      "contentHash": "df36f7051335cd1e748b1b6463b7fdd3",
      "sourceName": "@openzeppelin/contracts/token/ERC20/IERC20.sol",
      "solcConfig": {
        "version": "0.8.20",
        "settings": {
          "optimizer": {
            "enabled": true,
            "runs": 200
          },
          "viaIR": true,
          "evmVersion": "paris",
          "outputSelection": {
            "*": {
              "*": [
                "abi",
                "evm.bytecode",
                "evm.deployedBytecode",
                "evm.methodIdentifiers",
                "metadata"
              ],
              "": [
                "ast"
              ]
            }
          }
        }
      },
      "imports": [],
      "versionPragmas": [
        "^0.8.0"
      ],
      "artifacts": [
        "IERC20"
      ]
    },
    "/home/jistriane/Documentos/StreamPay AI/StreamPay-AI/smart-contracts/node_modules/@openzeppelin/contracts/utils/Context.sol": {
      "lastModificationDate": 1765496180567,
      "contentHash": "f07feb4a44b1a4872370da5aa70e8e46",
      "sourceName": "@openzeppelin/contracts/utils/Context.sol",
      "solcConfig": {
        "version": "0.8.20",
        "settings": {
          "optimizer": {
            "enabled": true,
            "runs": 200
          },
          "viaIR": true,
          "evmVersion": "paris",
          "outputSelection": {
            "*": {
              "*": [
                "abi",
                "evm.bytecode",
                "evm.deployedBytecode",
                "evm.methodIdentifiers",
                "metadata"
              ],
              "": [
                "ast"
              ]
            }
          }
        }
      },
      "imports": [],
      "versionPragmas": [
        "^0.8.0"
      ],
      "artifacts": [
        "Context"
      ]
    },
    "/home/jistriane/Documentos/StreamPay AI/StreamPay-AI/smart-contracts/node_modules/@openzeppelin/contracts/token/ERC20/extensions/IERC20Metadata.sol": {
      "lastModificationDate": 1765496182715,
      "contentHash": "909ab67fc5c25033fe6cd364f8c056f9",
      "sourceName": "@openzeppelin/contracts/token/ERC20/extensions/IERC20Metadata.sol",
      "solcConfig": {
        "version": "0.8.20",
        "settings": {
          "optimizer": {
            "enabled": true,
            "runs": 200
          },
          "viaIR": true,
          "evmVersion": "paris",
          "outputSelection": {
            "*": {
              "*": [
                "abi",
                "evm.bytecode",
                "evm.deployedBytecode",
                "evm.methodIdentifiers",
                "metadata"
              ],
              "": [
                "ast"
              ]
            }
          }
        }
      },
      "imports": [
        "../IERC20.sol"
      ],
      "versionPragmas": [
        "^0.8.0"
      ],
      "artifacts": [
        "IERC20Metadata"
      ]
    },
    "/home/jistriane/Documentos/StreamPay AI/StreamPay-AI/smart-contracts/node_modules/@openzeppelin/contracts/token/ERC20/utils/SafeERC20.sol": {
      "lastModificationDate": 1765496183385,
      "contentHash": "1b5d667d3740d866eca0352758e59827",
      "sourceName": "@openzeppelin/contracts/token/ERC20/utils/SafeERC20.sol",
      "solcConfig": {
        "version": "0.8.20",
        "settings": {
          "optimizer": {
            "enabled": true,
            "runs": 200
          },
          "viaIR": true,
          "evmVersion": "paris",
          "outputSelection": {
            "*": {
              "*": [
                "abi",
                "evm.bytecode",
                "evm.deployedBytecode",
                "evm.methodIdentifiers",
                "metadata"
              ],
              "": [
                "ast"
              ]
            }
          }
        }
      },
      "imports": [
        "../IERC20.sol",
        "../extensions/IERC20Permit.sol",
        "../../../utils/Address.sol"
      ],
      "versionPragmas": [
        "^0.8.0"
      ],
      "artifacts": [
        "SafeERC20"
      ]
    },
    "/home/jistriane/Documentos/StreamPay AI/StreamPay-AI/smart-contracts/node_modules/@openzeppelin/contracts/utils/Address.sol": {
      "lastModificationDate": 1765496180437,
      "contentHash": "211ffd288c1588ba8c10eae668ca3c66",
      "sourceName": "@openzeppelin/contracts/utils/Address.sol",
      "solcConfig": {
        "version": "0.8.20",
        "settings": {
          "optimizer": {
            "enabled": true,
            "runs": 200
          },
          "viaIR": true,
          "evmVersion": "paris",
          "outputSelection": {
            "*": {
              "*": [
                "abi",
                "evm.bytecode",
                "evm.deployedBytecode",
                "evm.methodIdentifiers",
                "metadata"
              ],
              "": [
                "ast"
              ]
            }
          }
        }
      },
      "imports": [],
      "versionPragmas": [
        "^0.8.1"
      ],
      "artifacts": [
        "Address"
      ]
    },
    "/home/jistriane/Documentos/StreamPay AI/StreamPay-AI/smart-contracts/node_modules/@openzeppelin/contracts/token/ERC20/extensions/IERC20Permit.sol": {
      "lastModificationDate": 1765496182760,
      "contentHash": "525fcdad8d171312933f47baf01d1ed8",
      "sourceName": "@openzeppelin/contracts/token/ERC20/extensions/IERC20Permit.sol",
      "solcConfig": {
        "version": "0.8.20",
        "settings": {
          "optimizer": {
            "enabled": true,
            "runs": 200
          },
          "viaIR": true,
          "evmVersion": "paris",
          "outputSelection": {
            "*": {
              "*": [
                "abi",
                "evm.bytecode",
                "evm.deployedBytecode",
                "evm.methodIdentifiers",
                "metadata"
              ],
              "": [
                "ast"
              ]
            }
          }
        }
      },
      "imports": [],
      "versionPragmas": [
        "^0.8.0"
      ],
      "artifacts": [
        "IERC20Permit"
      ]
    },
    "/home/jistriane/Documentos/StreamPay AI/StreamPay-AI/smart-contracts/contracts/SwapRouter.sol": {
      "lastModificationDate": 1765761695421,
      "contentHash": "7fc090dd2aab29ff07a871d59464c64e",
      "sourceName": "contracts/SwapRouter.sol",
      "solcConfig": {
        "version": "0.8.20",
        "settings": {
          "optimizer": {
            "enabled": true,
            "runs": 200
          },
          "viaIR": true,
          "evmVersion": "paris",
          "outputSelection": {
            "*": {
              "*": [
                "abi",
                "evm.bytecode",
                "evm.deployedBytecode",
                "evm.methodIdentifiers",
                "metadata"
              ],
              "": [
                "ast"
              ]
            }
          }
        }
      },
      "imports": [
        "@openzeppelin/contracts/token/ERC20/IERC20.sol",
        "@openzeppelin/contracts/token/ERC20/utils/SafeERC20.sol",
        "@openzeppelin/contracts/security/ReentrancyGuard.sol",
        "@openzeppelin/contracts/security/Pausable.sol",
        "@openzeppelin/contracts/access/Ownable.sol"
      ],
      "versionPragmas": [
        "^0.8.20"
      ],
      "artifacts": [
        "AggregatorV3Interface",
        "ISwapRouter",
        "SwapRouter"
      ]
    },
    "/home/jistriane/Documentos/StreamPay AI/StreamPay-AI/smart-contracts/node_modules/@openzeppelin/contracts/security/ReentrancyGuard.sol": {
      "lastModificationDate": 1765496183318,
      "contentHash": "1535f8c0c68463f8c1b5239f7584e71f",
      "sourceName": "@openzeppelin/contracts/security/ReentrancyGuard.sol",
      "solcConfig": {
        "version": "0.8.20",
        "settings": {
          "optimizer": {
            "enabled": true,
            "runs": 200
          },
          "viaIR": true,
          "evmVersion": "paris",
          "outputSelection": {
            "*": {
              "*": [
                "abi",
                "evm.bytecode",
                "evm.deployedBytecode",
                "evm.methodIdentifiers",
                "metadata"
              ],
              "": [
                "ast"
              ]
            }
          }
        }
      },
      "imports": [],
      "versionPragmas": [
        "^0.8.0"
      ],
      "artifacts": [
        "ReentrancyGuard"
      ]
    },
    "/home/jistriane/Documentos/StreamPay AI/StreamPay-AI/smart-contracts/node_modules/@openzeppelin/contracts/security/Pausable.sol": {
      "lastModificationDate": 1765496183269,
      "contentHash": "25c8108f36fdd472bc78d4c4af240c11",
      "sourceName": "@openzeppelin/contracts/security/Pausable.sol",
      "solcConfig": {
        "version": "0.8.20",
        "settings": {
          "optimizer": {
            "enabled": true,
            "runs": 200
          },
          "viaIR": true,
          "evmVersion": "paris",
          "outputSelection": {
            "*": {
              "*": [
                "abi",
                "evm.bytecode",
                "evm.deployedBytecode",
                "evm.methodIdentifiers",
                "metadata"
              ],
              "": [
                "ast"
              ]
            }
          }
        }
      },
      "imports": [
        "../utils/Context.sol"
      ],
      "versionPragmas": [
        "^0.8.0"
      ],
      "artifacts": [
        "Pausable"
      ]
    },
    "/home/jistriane/Documentos/StreamPay AI/StreamPay-AI/smart-contracts/node_modules/@openzeppelin/contracts/access/Ownable.sol": {
      "lastModificationDate": 1765496183255,
      "contentHash": "5a20b2cad87ddb61c7a3a6af21289e28",
      "sourceName": "@openzeppelin/contracts/access/Ownable.sol",
      "solcConfig": {
        "version": "0.8.20",
        "settings": {
          "optimizer": {
            "enabled": true,
            "runs": 200
          },
          "viaIR": true,
          "evmVersion": "paris",
          "outputSelection": {
            "*": {
              "*": [
                "abi",
                "evm.bytecode",
                "evm.deployedBytecode",
                "evm.methodIdentifiers",
                "metadata"
              ],
              "": [
                "ast"
              ]
            }
          }
        }
      },
      "imports": [
        "../utils/Context.sol"
      ],
      "versionPragmas": [
        "^0.8.0"
      ],
      "artifacts": [
        "Ownable"
      ]
    },
    "/home/jistriane/Documentos/StreamPay AI/StreamPay-AI/smart-contracts/contracts/StreamPayCore.sol": {
      "lastModificationDate": 1765496873028,
      "contentHash": "ff3d50950ecdef004bc7830f7eaf522b",
      "sourceName": "contracts/StreamPayCore.sol",
      "solcConfig": {
        "version": "0.8.20",
        "settings": {
          "optimizer": {
            "enabled": true,
            "runs": 200
          },
          "viaIR": true,
          "evmVersion": "paris",
          "outputSelection": {
            "*": {
              "*": [
                "abi",
                "evm.bytecode",
                "evm.deployedBytecode",
                "evm.methodIdentifiers",
                "metadata"
              ],
              "": [
                "ast"
              ]
            }
          }
        }
      },
      "imports": [
        "@openzeppelin/contracts/token/ERC20/IERC20.sol",
        "@openzeppelin/contracts/token/ERC20/utils/SafeERC20.sol",
        "@openzeppelin/contracts/security/ReentrancyGuard.sol",
        "@openzeppelin/contracts/security/Pausable.sol",
        "@openzeppelin/contracts/access/Ownable.sol"
      ],
      "versionPragmas": [
        "^0.8.20"
      ],
      "artifacts": [
        "StreamPayCore"
      ]
    },
    "/home/jistriane/Documentos/StreamPay AI/StreamPay-AI/smart-contracts/contracts/PoolManager.sol": {
      "lastModificationDate": 1765761695420,
      "contentHash": "69f243a00b6fc13d69a67cf4c465a493",
      "sourceName": "contracts/PoolManager.sol",
      "solcConfig": {
        "version": "0.8.20",
        "settings": {
          "optimizer": {
            "enabled": true,
            "runs": 200
          },
          "viaIR": true,
          "evmVersion": "paris",
          "outputSelection": {
            "*": {
              "*": [
                "abi",
                "evm.bytecode",
                "evm.deployedBytecode",
                "evm.methodIdentifiers",
                "metadata"
              ],
              "": [
                "ast"
              ]
            }
          }
        }
      },
      "imports": [
        "@openzeppelin/contracts/token/ERC20/IERC20.sol",
        "@openzeppelin/contracts/token/ERC20/utils/SafeERC20.sol",
        "@openzeppelin/contracts/security/ReentrancyGuard.sol",
        "@openzeppelin/contracts/security/Pausable.sol",
        "@openzeppelin/contracts/access/Ownable.sol"
      ],
      "versionPragmas": [
        "^0.8.20"
      ],
      "artifacts": [
        "INonfungiblePositionManager",
        "IUniswapV3Factory",
        "IUniswapV3Pool",
        "PoolManager"
      ]
    },
    "/home/jistriane/Documentos/StreamPay AI/StreamPay-AI/smart-contracts/contracts/LiquidityPool.sol": {
      "lastModificationDate": 1765761695420,
      "contentHash": "06b5d90232edd67fcfe97efe0c6b861f",
      "sourceName": "contracts/LiquidityPool.sol",
      "solcConfig": {
        "version": "0.8.20",
        "settings": {
          "optimizer": {
            "enabled": true,
            "runs": 200
          },
          "viaIR": true,
          "evmVersion": "paris",
          "outputSelection": {
            "*": {
              "*": [
                "abi",
                "evm.bytecode",
                "evm.deployedBytecode",
                "evm.methodIdentifiers",
                "metadata"
              ],
              "": [
                "ast"
              ]
            }
          }
        }
      },
      "imports": [
        "@openzeppelin/contracts/token/ERC20/IERC20.sol",
        "@openzeppelin/contracts/token/ERC20/utils/SafeERC20.sol",
        "@openzeppelin/contracts/security/ReentrancyGuard.sol",
        "@openzeppelin/contracts/security/Pausable.sol",
        "@openzeppelin/contracts/access/Ownable.sol"
      ],
      "versionPragmas": [
        "^0.8.20"
      ],
      "artifacts": [
        "LiquidityPool"
      ]
    }
  }
}
